LICENSE
README.rst
setup.py
pdf_toolbox/__init__.py
pdf_toolbox.egg-info/PKG-INFO
pdf_toolbox.egg-info/SOURCES.txt
pdf_toolbox.egg-info/dependency_links.txt
pdf_toolbox.egg-info/requires.txt
pdf_toolbox.egg-info/top_level.txt
pdf_toolbox/pdf/__init__.py
pdf_toolbox/pdf/domain/__init__.py
pdf_toolbox/pdf/domain/pdfreader.py
pdf_toolbox/pdf/readers/__init__.py
pdf_toolbox/pdf/readers/filereader.py
pdf_toolbox/report_storage/__init__.py
pdf_toolbox/report_storage/domain/__init__.py
pdf_toolbox/report_storage/domain/storage.py
pdf_toolbox/report_storage/storages/__init__.py
pdf_toolbox/report_storage/storages/json_storage.py
pdf_toolbox/shared/__init__.py
pdf_toolbox/shared/utils.py
pdf_toolbox/tests/__init__.py
pdf_toolbox/tests/conftest.py
pdf_toolbox/tests/test_generic_workflow.py
pdf_toolbox/text_extraction/__init__.py
pdf_toolbox/text_extraction/utils.py
pdf_toolbox/text_extraction/domain/__init__.py
pdf_toolbox/text_extraction/domain/report_parser.py
pdf_toolbox/text_extraction/report_parsers/__init__.py
pdf_toolbox/text_extraction/report_parsers/challenge_parser.py