Metadata-Version: 2.1
Name: pdf-toolbox
Version: 0.1.0
Summary: A package to extract and store data from PDFs
Home-page: UNKNOWN
Author: Samuel López Saura
Author-email: samuellopezsaura@gmail.com
License: MIT
Platform: UNKNOWN
License-File: LICENSE
